{
  "openapi": "3.1.0",
  "info": {
    "title": "OpenHuman API",
    "description": "OpenHuman \u2014 API backend",
    "version": "0.1.0"
  },
  "paths": {
    "/api/health": {
      "get": {
        "tags": [
          "health"
        ],
        "summary": "Health Check",
        "operationId": "health-health_check",
        "responses": {
          "200": {
            "description": "Successful Response",
            "content": {
              "application/json": {
                "schema": {
                  "$ref": "#/components/schemas/HealthResponse"
                }
              }
            }
          }
        }
      }
    }
  },
  "components": {
    "schemas": {
      "HealthResponse": {
        "properties": {
          "status": {
            "type": "string",
            "title": "Status"
          },
          "version": {
            "type": "string",
            "title": "Version"
          }
        },
        "type": "object",
        "required": [
          "status",
          "version"
        ],
        "title": "HealthResponse"
      }
    }
  },
  "servers": [
    {
      "url": "http://localhost:8000",
      "description": "Development"
    }
  ]
}